extractor/__init__.py
models/__init__.py
ai_question_extractor-1.0.1.dist-info/LICENSE
ai_question_extractor-1.0.1.dist-info/METADATA
ai_question_extractor-1.0.1.dist-info/WHEEL
ai_question_extractor-1.0.1.dist-info/RECORD
